pmm_cfg_gen/.gitignore
pmm_cfg_gen/__init__.py
pmm_cfg_gen/config_default.yaml
pmm_cfg_gen/logging.yaml
pmm_cfg_gen/templates/library.json.j2
pmm_cfg_gen/templates/movie.collection.json.j2
pmm_cfg_gen/templates/movie.collection.yaml.j2
pmm_cfg_gen/templates/movie.metadata.json.j2
pmm_cfg_gen/templates/movie.metadata.yaml.j2
pmm_cfg_gen/templates/music.collection.json.j2
pmm_cfg_gen/templates/music.metadata.json.j2
pmm_cfg_gen/templates/report.collection.html.j2
pmm_cfg_gen/templates/report.collection.json.j2
pmm_cfg_gen/templates/report.library.html.j2
pmm_cfg_gen/templates/report.metadata.html.j2
pmm_cfg_gen/templates/report.metadata.json.j2
pmm_cfg_gen/templates/show.collection.json.j2
pmm_cfg_gen/templates/show.collection.yaml.j2
pmm_cfg_gen/templates/show.metadata.json.j2
pmm_cfg_gen/templates/show.metadata.yaml.j2
pmm_cfg_gen/templates/template.collection.yaml.j2
pmm_cfg_gen/utils/__init__.py
pmm_cfg_gen/utils/cli_args.py
pmm_cfg_gen/utils/file_utils.py
pmm_cfg_gen/utils/logging_utils.py
pmm_cfg_gen/utils/plex.py
pmm_cfg_gen/utils/plex_cache.py
pmm_cfg_gen/utils/plex_stats.py
pmm_cfg_gen/utils/plex_utils.py
pmm_cfg_gen/utils/pmm_utils.py
pmm_cfg_gen/utils/settings_utils_v1.py
pmm_cfg_gen/utils/template_filters.py
pmm_cfg_gen/utils/template_manager.py
pmm_cfg_gen/utils/time_span.py
pmm_cfg_gen/utils/timer.py
pmm_cfg_gen/utils/tmdb_utils.py
pmm_cfg_gen/utils/trakt_utils.py
pmm_cfg_gen/utils/tvdb_utils.py
pmm_cfg_gen-0.2.7.dist-info/LICENSE
pmm_cfg_gen-0.2.7.dist-info/METADATA
pmm_cfg_gen-0.2.7.dist-info/WHEEL
pmm_cfg_gen-0.2.7.dist-info/entry_points.txt
pmm_cfg_gen-0.2.7.dist-info/RECORD
