Metadata-Version: 2.1
Name: pmm-cfg-gen
Version: 0.2.7
Summary: A script to help automatically generate Plex Meta Manager configuration files for your libraries
Home-page: https://github.com/ravensorb/Plex-Meta-Manager-Config-Generator
License: GPL-3.0-or-later
Keywords: pmm,plex-meta-manager,plex
Author: Shawn Anderson
Author-email: sanderson@eye-catcher.com
Requires-Python: >=3.10,<4.0
Classifier: License :: OSI Approved :: GNU General Public License v3 or later (GPLv3+)
Classifier: Programming Language :: Python :: 3
Classifier: Programming Language :: Python :: 3.10
Classifier: Programming Language :: Python :: 3.11
Classifier: Topic :: Utilities
Requires-Dist: coloredlogs (>=15.0.1,<16.0.0)
Requires-Dist: confuse (>=2.0.1,<3.0.0)
Requires-Dist: dotty (>=0.1.0,<0.2.0)
Requires-Dist: dotty-dict
Requires-Dist: expandvars (>=0.9.0,<0.10.0)
Requires-Dist: importlib-resources (>=5.12.0,<6.0.0)
Requires-Dist: jinja2
Requires-Dist: json-fix (>=0.5.2,<0.6.0)
Requires-Dist: jsonpickle (>=3.0.1,<4.0.0)
Requires-Dist: plexapi (>=4.14.0,<5.0.0)
Requires-Dist: python-dotenv (>=1.0.0,<2.0.0)
Requires-Dist: readchar (>=4.0.5,<5.0.0)
Requires-Dist: ruamel-yaml (>=0.17.21,<0.18.0)
Requires-Dist: themoviedb (>=0.3.3,<0.4.0)
Project-URL: Repository, https://github.com/ravensorb/Plex-Meta-Manager-Config-Generator
